{
  "ComponentIndexes": {
    "Footer": 5,
    "Header": 6,
    "Header_homepage": 7,
    "Page_header": 8,
    "Welcome": 9
  },
  "ControlUniqueGuids": {},
  "ControlUniqueIds": {
    "__PowerAppsId___DataCard2": 259,
    "Active_DataCard2": 264,
    "AddButton": 94,
    "AddButton_1": 93,
    "AddButton_4": 150,
    "App": 1,
    "Attachments_DataCard2": 269,
    "Branding/Styling": 21,
    "btnCreateNewUser": 32,
    "btnViewExistingUser": 33,
    "Company_DataCard1": 65,
    "Company_DataCard3": 130,
    "Company_DataCard4": 239,
    "DataCardKey1": 107,
    "DataCardKey19": 112,
    "DataCardKey2": 47,
    "DataCardKey20": 117,
    "DataCardKey21": 122,
    "DataCardKey22": 127,
    "DataCardKey23": 132,
    "DataCardKey24": 137,
    "DataCardKey25": 142,
    "DataCardKey26": 147,
    "DataCardKey3": 52,
    "DataCardKey30": 215,
    "DataCardKey31": 220,
    "DataCardKey32": 225,
    "DataCardKey33": 230,
    "DataCardKey34": 235,
    "DataCardKey35": 240,
    "DataCardKey36": 245,
    "DataCardKey37": 250,
    "DataCardKey38": 255,
    "DataCardKey39": 260,
    "DataCardKey4": 57,
    "DataCardKey40": 265,
    "DataCardKey41": 270,
    "DataCardKey5": 62,
    "DataCardKey6": 67,
    "DataCardKey7": 72,
    "DataCardKey8": 77,
    "DataCardKey9": 82,
    "DataCardValue10": 43,
    "DataCardValue11": 48,
    "DataCardValue12": 53,
    "DataCardValue13": 58,
    "DataCardValue14": 63,
    "DataCardValue15": 68,
    "DataCardValue16": 73,
    "DataCardValue17": 78,
    "DataCardValue18": 83,
    "DataCardValue19": 108,
    "DataCardValue20": 113,
    "DataCardValue21": 118,
    "DataCardValue22": 123,
    "DataCardValue23": 128,
    "DataCardValue24": 133,
    "DataCardValue25": 138,
    "DataCardValue26": 143,
    "DataCardValue27": 148,
    "DataCardValue31": 216,
    "DataCardValue32": 221,
    "DataCardValue33": 226,
    "DataCardValue34": 231,
    "DataCardValue35": 236,
    "DataCardValue36": 241,
    "DataCardValue37": 246,
    "DataCardValue38": 251,
    "DataCardValue39": 256,
    "DataCardValue40": 261,
    "DataCardValue41": 266,
    "DataCardValue42": 271,
    "ErrorMessage1": 44,
    "ErrorMessage19": 109,
    "ErrorMessage2": 49,
    "ErrorMessage20": 114,
    "ErrorMessage21": 119,
    "ErrorMessage22": 124,
    "ErrorMessage23": 129,
    "ErrorMessage24": 134,
    "ErrorMessage25": 139,
    "ErrorMessage26": 144,
    "ErrorMessage27": 149,
    "ErrorMessage3": 54,
    "ErrorMessage31": 217,
    "ErrorMessage32": 222,
    "ErrorMessage33": 227,
    "ErrorMessage34": 232,
    "ErrorMessage35": 237,
    "ErrorMessage36": 242,
    "ErrorMessage37": 247,
    "ErrorMessage38": 252,
    "ErrorMessage39": 257,
    "ErrorMessage4": 59,
    "ErrorMessage40": 262,
    "ErrorMessage41": 267,
    "ErrorMessage42": 272,
    "ErrorMessage5": 64,
    "ErrorMessage6": 69,
    "ErrorMessage7": 74,
    "ErrorMessage8": 79,
    "ErrorMessage9": 84,
    "First": 42,
    "First Name_DataCard1": 40,
    "First Name_DataCard3": 105,
    "First Name_DataCard4": 214,
    "Footer": 4,
    "Footer_1": 95,
    "Footer_2": 34,
    "Footer_3": 151,
    "Form1": 39,
    "Form2": 213,
    "Form3": 104,
    "Full Name_DataCard1": 55,
    "Full Name_DataCard3": 120,
    "Full Name_DataCard4": 229,
    "Gallery1": 274,
    "Gallery2": 98,
    "galleryTemplate1": 91,
    "galleryTemplate2": 99,
    "galleryTemplate3": 275,
    "Header": 8,
    "Header_homepage": 12,
    "Header_homepage_1": 31,
    "Host": 3,
    "Icon1": 38,
    "Icon1_3": 9,
    "Icon3_2": 17,
    "Icon3_3": 10,
    "Image1": 90,
    "Image2": 101,
    "Image3": 276,
    "Image4_1": 13,
    "Image4_2": 16,
    "Job Title_DataCard1": 60,
    "Job Title_DataCard3": 125,
    "Job Title_DataCard4": 234,
    "Label1_2": 20,
    "Label12_1": 14,
    "Label12_2": 18,
    "Label12_3": 11,
    "Label2": 23,
    "Label2_1": 26,
    "Label3_2": 5,
    "Label3_3": 6,
    "Label3_4": 7,
    "Last Name_DataCard1": 50,
    "Last Name_DataCard3": 115,
    "Last Name_DataCard4": 224,
    "NextArrow1": 88,
    "NextArrow2": 279,
    "Nickname/Alias_DataCard1": 45,
    "Nickname/Alias_DataCard3": 110,
    "Nickname/Alias_DataCard4": 219,
    "NIS_BLUE": 25,
    "NIS_LOGO": 24,
    "NIS_RED": 22,
    "Page_header": 15,
    "Page_header_1": 36,
    "Page_header_2": 97,
    "Rectangle1": 86,
    "Rectangle2": 100,
    "Rectangle3": 281,
    "RemoveButton": 92,
    "SAMPLE_BUTTON": 27,
    "Screen1": 212,
    "scrHome": 30,
    "scrManager": 35,
    "scrUser": 96,
    "Search_1": 37,
    "Separator1": 87,
    "Separator2": 280,
    "StaffGallery": 85,
    "StarVisible1": 41,
    "StarVisible19": 106,
    "StarVisible2": 46,
    "StarVisible20": 111,
    "StarVisible21": 116,
    "StarVisible22": 121,
    "StarVisible23": 126,
    "StarVisible24": 131,
    "StarVisible25": 136,
    "StarVisible26": 141,
    "StarVisible27": 146,
    "StarVisible3": 51,
    "StarVisible31": 218,
    "StarVisible32": 223,
    "StarVisible33": 228,
    "StarVisible34": 233,
    "StarVisible35": 238,
    "StarVisible36": 243,
    "StarVisible37": 248,
    "StarVisible38": 253,
    "StarVisible39": 258,
    "StarVisible4": 56,
    "StarVisible40": 263,
    "StarVisible41": 268,
    "StarVisible42": 273,
    "StarVisible5": 61,
    "StarVisible6": 66,
    "StarVisible7": 71,
    "StarVisible8": 76,
    "StarVisible9": 81,
    "Subtitle1": 278,
    "Subtitle2": 103,
    "Supervisor_DataCard1": 80,
    "Supervisor_DataCard3": 145,
    "Supervisor_DataCard4": 254,
    "Task Order #_DataCard1": 70,
    "Task Order #_DataCard3": 135,
    "Task Order #_DataCard4": 244,
    "Task Order Name_DataCard1": 75,
    "Task Order Name_DataCard3": 140,
    "Task Order Name_DataCard4": 249,
    "Title1": 89,
    "Title2": 102,
    "Title3": 277,
    "Welcome": 19
  },
  "FunctionParamsInvariantScripts": {},
  "FunctionParamsInvariantScriptsOnInstances": {},
  "HeaderLastSavedDateTimeUTC": "08/01/2023 14:29:27",
  "IsLegacyComponentAllowGlobalScopeCase": false,
  "LocalConnectionIDReferences": {
    "45d1dcd9-88a7-4380-8344-d6c45bb85cec": "\"/providers/microsoft.powerapps/apis/shared_sharepointonline/connections/6659089814b446f6b155f9f8250658c8\"",
    "77a13ace-fe30-4103-9667-ccd761a7e3e1": "\"/providers/microsoft.powerapps/apis/shared_excelonlinebusiness/connections/5c72687c21f14d8daf2ec610d31bd314\""
  },
  "LocalDatabaseReferencesAsEmpty": false,
  "LocalResourceFileNames": {
    "chartim": "0001.png",
    "ia_comments": "0003.png",
    "iaform_first-1": "0002.png",
    "idasda-1": "0004.png",
    "Logo": "0005.jpg",
    "Logo_1": "0006.jpg",
    "logo_2": "0007.png",
    "NIS_Blue_logo": "0008.png",
    "NIS_New_2018_Logo": "0009.png",
    "snippemtasd": "0010.png",
    "snippemtasd_1": "0011.png"
  },
  "LocalResourceRootPaths": {
    "chartim": "https://docserverpwaprodeus.blob.core.windows.net/4c9675f6-4f6c-45ce-a4fc-173d47b65012-1/resource/Assets0Images00001.png?sv=2018-03-28&sr=b&sig=BwmXN9hA75qiccdlOFv8USaDZbLJfYADeVb1Hsszy9k%3D&spr=https&se=2023-08-02T14%3A37%3A36Z&sp=r",
    "ia_comments": "https://docserverpwaprodeus.blob.core.windows.net/4c9675f6-4f6c-45ce-a4fc-173d47b65012-1/resource/Assets0Images00003.png?sv=2018-03-28&sr=b&sig=0Z%2FkbvfnC2VnQVAal8Qetsp6dNWz%2BgaNaF8KUee3PZs%3D&spr=https&se=2023-08-02T14%3A37%3A36Z&sp=r",
    "iaform_first-1": "https://docserverpwaprodeus.blob.core.windows.net/4c9675f6-4f6c-45ce-a4fc-173d47b65012-1/resource/Assets0Images00002.png?sv=2018-03-28&sr=b&sig=rrGKbCqzz95xl5gNYfPz1%2BUUepLM48xRz1E1YEtzLYY%3D&spr=https&se=2023-08-02T14%3A37%3A36Z&sp=r",
    "idasda-1": "https://docserverpwaprodeus.blob.core.windows.net/4c9675f6-4f6c-45ce-a4fc-173d47b65012-1/resource/Assets0Images00004.png?sv=2018-03-28&sr=b&sig=S3VP0Pb4QGtAbHmwbrE4qa8xUtcf%2BJPnH%2Benw6xUJdc%3D&spr=https&se=2023-08-02T14%3A37%3A36Z&sp=r",
    "Logo": "https://docserverpwaprodeus.blob.core.windows.net/4c9675f6-4f6c-45ce-a4fc-173d47b65012-1/resource/Assets0Images00005.jpg?sv=2018-03-28&sr=b&sig=6Tj4NC8qwyXT%2F%2BFiXgTRRs45uK%2BHZ8f%2BbWvtHdY6BrE%3D&spr=https&se=2023-08-02T14%3A37%3A36Z&sp=r",
    "Logo_1": "https://docserverpwaprodeus.blob.core.windows.net/4c9675f6-4f6c-45ce-a4fc-173d47b65012-1/resource/Assets0Images00006.jpg?sv=2018-03-28&sr=b&sig=8K%2F7qi0x9jvyrboRPlCTdbm4A8CqK5qnns5nd9b0th4%3D&spr=https&se=2023-08-02T14%3A37%3A36Z&sp=r",
    "logo_2": "https://docserverpwaprodeus.blob.core.windows.net/4c9675f6-4f6c-45ce-a4fc-173d47b65012-1/resource/Assets0Images00007.png?sv=2018-03-28&sr=b&sig=g1aw2tNCF8XzulsZ2TqgBj8MeJdr%2FZuHhsABG7O5u2c%3D&spr=https&se=2023-08-02T14%3A37%3A36Z&sp=r",
    "NIS_Blue_logo": "https://docserverpwaprodeus.blob.core.windows.net/4c9675f6-4f6c-45ce-a4fc-173d47b65012-1/resource/Assets0Images00008.png?sv=2018-03-28&sr=b&sig=zvUfDndw2VoSPBNOWKJUWFWpvo38XwTFjTgx74TErKI%3D&spr=https&se=2023-08-02T14%3A37%3A36Z&sp=r",
    "NIS_New_2018_Logo": "https://docserverpwaprodeus.blob.core.windows.net/4c9675f6-4f6c-45ce-a4fc-173d47b65012-1/resource/Assets0Images00009.png?sv=2018-03-28&sr=b&sig=3n3%2BRnSGq%2BZSCOxVoRtBVkFmc85p0kf05ernNg1W5vk%3D&spr=https&se=2023-08-02T14%3A37%3A36Z&sp=r",
    "snippemtasd": "https://docserverpwaprodeus.blob.core.windows.net/4c9675f6-4f6c-45ce-a4fc-173d47b65012-1/resource/Assets0Images00010.png?sv=2018-03-28&sr=b&sig=sn8LNO9tIzwbqihpI9hIeAwmxLRKhObnHfrH4lEU%2Fxg%3D&spr=https&se=2023-08-02T14%3A37%3A36Z&sp=r",
    "snippemtasd_1": "https://docserverpwaprodeus.blob.core.windows.net/4c9675f6-4f6c-45ce-a4fc-173d47b65012-1/resource/Assets0Images00011.png?sv=2018-03-28&sr=b&sig=Z3X6NB4l%2BYTmOU0qLLEsDfdi2Z5g6Af96pmcXjc%2BLp0%3D&spr=https&se=2023-08-02T14%3A37%3A36Z&sp=r"
  },
  "OrderComponentMetadata": {
    "1bed1ce7b7404ccfafa05f0c3d1eabfe": 0,
    "1fe5cb6d6d5c424db75d7e843c1d26d9": 1,
    "5215c742aeea4048a853e8e745619b28": 2,
    "b9e9c7020717474292bbfd84c70fae58": 3,
    "e13589d35384415b90784ea27e3eb7e4": 4
  },
  "OrderComponentTemplate": {
    "1bed1ce7b7404ccfafa05f0c3d1eabfe": 0,
    "1fe5cb6d6d5c424db75d7e843c1d26d9": 1,
    "5215c742aeea4048a853e8e745619b28": 2,
    "b9e9c7020717474292bbfd84c70fae58": 3,
    "e13589d35384415b90784ea27e3eb7e4": 4
  },
  "OrderDataSource": {
    "ComboBoxSample": 5,
    "CustomGallerySample": 0,
    "StaffTable": 1,
    "StaffTable_1": 2,
    "StaffTable_2": 3,
    "USGS Roster 071823": 4
  },
  "OrderGroupControls": {},
  "OrderPcfTemplate": {},
  "OrderTemplate": {},
  "OrderXMLTemplate": {
    "attachments": 8,
    "button": 3,
    "combobox": 6,
    "form": 4,
    "gallery": 9,
    "icon": 10,
    "image": 2,
    "label": 1,
    "rectangle": 0,
    "text": 5,
    "toggleSwitch": 7
  },
  "OverridablePropertiesEntry": {
    "__PowerAppsId___DataCard2": {},
    "Active_DataCard2": {},
    "AddButton": {},
    "AddButton_1": {},
    "AddButton_4": {},
    "App": {},
    "Attachments_DataCard2": {},
    "Branding/Styling": {},
    "btnCreateNewUser": {},
    "btnViewExistingUser": {},
    "Company_DataCard1": {},
    "Company_DataCard3": {},
    "Company_DataCard4": {},
    "DataCardKey1": {},
    "DataCardKey19": {},
    "DataCardKey2": {},
    "DataCardKey20": {},
    "DataCardKey21": {},
    "DataCardKey22": {},
    "DataCardKey23": {},
    "DataCardKey24": {},
    "DataCardKey25": {},
    "DataCardKey26": {},
    "DataCardKey3": {},
    "DataCardKey30": {},
    "DataCardKey31": {},
    "DataCardKey32": {},
    "DataCardKey33": {},
    "DataCardKey34": {},
    "DataCardKey35": {},
    "DataCardKey36": {},
    "DataCardKey37": {},
    "DataCardKey38": {},
    "DataCardKey39": {},
    "DataCardKey4": {},
    "DataCardKey40": {},
    "DataCardKey41": {},
    "DataCardKey5": {},
    "DataCardKey6": {},
    "DataCardKey7": {},
    "DataCardKey8": {},
    "DataCardKey9": {},
    "DataCardValue10": {},
    "DataCardValue11": {},
    "DataCardValue12": {},
    "DataCardValue13": {},
    "DataCardValue14": {},
    "DataCardValue15": {},
    "DataCardValue16": {},
    "DataCardValue17": {},
    "DataCardValue18": {},
    "DataCardValue19": {},
    "DataCardValue20": {},
    "DataCardValue21": {},
    "DataCardValue22": {},
    "DataCardValue23": {},
    "DataCardValue24": {},
    "DataCardValue25": {},
    "DataCardValue26": {},
    "DataCardValue27": {},
    "DataCardValue31": {},
    "DataCardValue32": {},
    "DataCardValue33": {},
    "DataCardValue34": {},
    "DataCardValue35": {},
    "DataCardValue36": {},
    "DataCardValue37": {},
    "DataCardValue38": {},
    "DataCardValue39": {},
    "DataCardValue40": {},
    "DataCardValue41": {},
    "DataCardValue42": {},
    "ErrorMessage1": {},
    "ErrorMessage19": {},
    "ErrorMessage2": {},
    "ErrorMessage20": {},
    "ErrorMessage21": {},
    "ErrorMessage22": {},
    "ErrorMessage23": {},
    "ErrorMessage24": {},
    "ErrorMessage25": {},
    "ErrorMessage26": {},
    "ErrorMessage27": {},
    "ErrorMessage3": {},
    "ErrorMessage31": {},
    "ErrorMessage32": {},
    "ErrorMessage33": {},
    "ErrorMessage34": {},
    "ErrorMessage35": {},
    "ErrorMessage36": {},
    "ErrorMessage37": {},
    "ErrorMessage38": {},
    "ErrorMessage39": {},
    "ErrorMessage4": {},
    "ErrorMessage40": {},
    "ErrorMessage41": {},
    "ErrorMessage42": {},
    "ErrorMessage5": {},
    "ErrorMessage6": {},
    "ErrorMessage7": {},
    "ErrorMessage8": {},
    "ErrorMessage9": {},
    "First": {},
    "First Name_DataCard1": {},
    "First Name_DataCard3": {},
    "First Name_DataCard4": {},
    "Footer": {},
    "Footer_1": {},
    "Footer_2": {},
    "Footer_3": {},
    "Form1": {},
    "Form2": {},
    "Form3": {},
    "Full Name_DataCard1": {},
    "Full Name_DataCard3": {},
    "Full Name_DataCard4": {},
    "Gallery1": {},
    "Gallery2": {},
    "galleryTemplate1": {},
    "galleryTemplate2": {},
    "galleryTemplate3": {},
    "Header": {},
    "Header_homepage": {},
    "Header_homepage_1": {},
    "Host": {},
    "Icon1": {},
    "Icon1_3": {},
    "Icon3_2": {},
    "Icon3_3": {},
    "Image1": {},
    "Image2": {},
    "Image3": {},
    "Image4_1": {},
    "Image4_2": {},
    "Job Title_DataCard1": {},
    "Job Title_DataCard3": {},
    "Job Title_DataCard4": {},
    "Label1_2": {},
    "Label12_1": {},
    "Label12_2": {},
    "Label12_3": {},
    "Label2": {},
    "Label2_1": {},
    "Label3_2": {},
    "Label3_3": {},
    "Label3_4": {},
    "Last Name_DataCard1": {},
    "Last Name_DataCard3": {},
    "Last Name_DataCard4": {},
    "NextArrow1": {},
    "NextArrow2": {},
    "Nickname/Alias_DataCard1": {},
    "Nickname/Alias_DataCard3": {},
    "Nickname/Alias_DataCard4": {},
    "NIS_BLUE": {},
    "NIS_LOGO": {},
    "NIS_RED": {},
    "Page_header": {},
    "Page_header_1": {},
    "Page_header_2": {},
    "Rectangle1": {},
    "Rectangle2": {},
    "Rectangle3": {},
    "RemoveButton": {},
    "SAMPLE_BUTTON": {},
    "Screen1": {},
    "scrHome": {},
    "scrManager": {},
    "scrUser": {},
    "Search_1": {},
    "Separator1": {},
    "Separator2": {},
    "StaffGallery": {},
    "StarVisible1": {},
    "StarVisible19": {},
    "StarVisible2": {},
    "StarVisible20": {},
    "StarVisible21": {},
    "StarVisible22": {},
    "StarVisible23": {},
    "StarVisible24": {},
    "StarVisible25": {},
    "StarVisible26": {},
    "StarVisible27": {},
    "StarVisible3": {},
    "StarVisible31": {},
    "StarVisible32": {},
    "StarVisible33": {},
    "StarVisible34": {},
    "StarVisible35": {},
    "StarVisible36": {},
    "StarVisible37": {},
    "StarVisible38": {},
    "StarVisible39": {},
    "StarVisible4": {},
    "StarVisible40": {},
    "StarVisible41": {},
    "StarVisible42": {},
    "StarVisible5": {},
    "StarVisible6": {},
    "StarVisible7": {},
    "StarVisible8": {},
    "StarVisible9": {},
    "Subtitle1": {},
    "Subtitle2": {},
    "Supervisor_DataCard1": {},
    "Supervisor_DataCard3": {},
    "Supervisor_DataCard4": {},
    "Task Order #_DataCard1": {},
    "Task Order #_DataCard3": {},
    "Task Order #_DataCard4": {},
    "Task Order Name_DataCard1": {},
    "Task Order Name_DataCard3": {},
    "Task Order Name_DataCard4": {},
    "Title1": {},
    "Title2": {},
    "Title3": {},
    "Welcome": {}
  },
  "PCFDynamicSchemaForIRRetrievalEntry": {},
  "PCFTemplateEntry": {},
  "PublishOrderIndices": {
    "__PowerAppsId___DataCard2": 0,
    "Active_DataCard2": 0,
    "AddButton": 42,
    "AddButton_1": 41,
    "AddButton_4": 99,
    "App": 0,
    "Attachments_DataCard2": 0,
    "Branding/Styling": 20,
    "btnCreateNewUser": 31,
    "btnViewExistingUser": 32,
    "Company_DataCard1": 49,
    "Company_DataCard3": 111,
    "Company_DataCard4": 0,
    "DataCardKey1": 116,
    "DataCardKey19": 120,
    "DataCardKey2": 58,
    "DataCardKey20": 124,
    "DataCardKey21": 128,
    "DataCardKey22": 132,
    "DataCardKey23": 136,
    "DataCardKey24": 140,
    "DataCardKey25": 144,
    "DataCardKey26": 148,
    "DataCardKey3": 62,
    "DataCardKey30": 0,
    "DataCardKey31": 0,
    "DataCardKey32": 0,
    "DataCardKey33": 0,
    "DataCardKey34": 0,
    "DataCardKey35": 0,
    "DataCardKey36": 0,
    "DataCardKey37": 0,
    "DataCardKey38": 0,
    "DataCardKey39": 0,
    "DataCardKey4": 66,
    "DataCardKey40": 0,
    "DataCardKey41": 0,
    "DataCardKey5": 70,
    "DataCardKey6": 74,
    "DataCardKey7": 78,
    "DataCardKey8": 82,
    "DataCardKey9": 86,
    "DataCardValue10": 55,
    "DataCardValue11": 59,
    "DataCardValue12": 63,
    "DataCardValue13": 67,
    "DataCardValue14": 71,
    "DataCardValue15": 75,
    "DataCardValue16": 79,
    "DataCardValue17": 83,
    "DataCardValue18": 87,
    "DataCardValue19": 117,
    "DataCardValue20": 121,
    "DataCardValue21": 125,
    "DataCardValue22": 129,
    "DataCardValue23": 133,
    "DataCardValue24": 137,
    "DataCardValue25": 141,
    "DataCardValue26": 145,
    "DataCardValue27": 149,
    "DataCardValue31": 0,
    "DataCardValue32": 0,
    "DataCardValue33": 0,
    "DataCardValue34": 0,
    "DataCardValue35": 0,
    "DataCardValue36": 0,
    "DataCardValue37": 0,
    "DataCardValue38": 0,
    "DataCardValue39": 0,
    "DataCardValue40": 0,
    "DataCardValue41": 0,
    "DataCardValue42": 0,
    "ErrorMessage1": 56,
    "ErrorMessage19": 118,
    "ErrorMessage2": 60,
    "ErrorMessage20": 122,
    "ErrorMessage21": 126,
    "ErrorMessage22": 130,
    "ErrorMessage23": 134,
    "ErrorMessage24": 138,
    "ErrorMessage25": 142,
    "ErrorMessage26": 146,
    "ErrorMessage27": 150,
    "ErrorMessage3": 64,
    "ErrorMessage31": 0,
    "ErrorMessage32": 0,
    "ErrorMessage33": 0,
    "ErrorMessage34": 0,
    "ErrorMessage35": 0,
    "ErrorMessage36": 0,
    "ErrorMessage37": 0,
    "ErrorMessage38": 0,
    "ErrorMessage39": 0,
    "ErrorMessage4": 68,
    "ErrorMessage40": 0,
    "ErrorMessage41": 0,
    "ErrorMessage42": 0,
    "ErrorMessage5": 72,
    "ErrorMessage6": 76,
    "ErrorMessage7": 80,
    "ErrorMessage8": 84,
    "ErrorMessage9": 88,
    "First": 54,
    "First Name_DataCard1": 44,
    "First Name_DataCard3": 106,
    "First Name_DataCard4": 0,
    "Footer": 1,
    "Footer_1": 43,
    "Footer_2": 33,
    "Footer_3": 100,
    "Form1": 38,
    "Form2": 0,
    "Form3": 98,
    "Full Name_DataCard1": 47,
    "Full Name_DataCard3": 109,
    "Full Name_DataCard4": 0,
    "Gallery1": 0,
    "Gallery2": 97,
    "galleryTemplate1": 94,
    "galleryTemplate2": 101,
    "galleryTemplate3": 0,
    "Header": 5,
    "Header_homepage": 9,
    "Header_homepage_1": 30,
    "Host": 0,
    "Icon1": 37,
    "Icon1_3": 6,
    "Icon3_2": 14,
    "Icon3_3": 7,
    "Image1": 93,
    "Image2": 103,
    "Image3": 0,
    "Image4_1": 10,
    "Image4_2": 13,
    "Job Title_DataCard1": 48,
    "Job Title_DataCard3": 110,
    "Job Title_DataCard4": 0,
    "Label1_2": 17,
    "Label12_1": 11,
    "Label12_2": 15,
    "Label12_3": 8,
    "Label2": 22,
    "Label2_1": 25,
    "Label3_2": 2,
    "Label3_3": 3,
    "Label3_4": 4,
    "Last Name_DataCard1": 46,
    "Last Name_DataCard3": 108,
    "Last Name_DataCard4": 0,
    "NextArrow1": 91,
    "NextArrow2": 0,
    "Nickname/Alias_DataCard1": 45,
    "Nickname/Alias_DataCard3": 107,
    "Nickname/Alias_DataCard4": 0,
    "NIS_BLUE": 24,
    "NIS_LOGO": 23,
    "NIS_RED": 21,
    "Page_header": 12,
    "Page_header_1": 35,
    "Page_header_2": 96,
    "Rectangle1": 89,
    "Rectangle2": 102,
    "Rectangle3": 0,
    "RemoveButton": 40,
    "SAMPLE_BUTTON": 26,
    "Screen1": 0,
    "scrHome": 29,
    "scrManager": 34,
    "scrUser": 95,
    "Search_1": 36,
    "Separator1": 90,
    "Separator2": 0,
    "StaffGallery": 39,
    "StarVisible1": 53,
    "StarVisible19": 115,
    "StarVisible2": 57,
    "StarVisible20": 119,
    "StarVisible21": 123,
    "StarVisible22": 127,
    "StarVisible23": 131,
    "StarVisible24": 135,
    "StarVisible25": 139,
    "StarVisible26": 143,
    "StarVisible27": 147,
    "StarVisible3": 61,
    "StarVisible31": 0,
    "StarVisible32": 0,
    "StarVisible33": 0,
    "StarVisible34": 0,
    "StarVisible35": 0,
    "StarVisible36": 0,
    "StarVisible37": 0,
    "StarVisible38": 0,
    "StarVisible39": 0,
    "StarVisible4": 65,
    "StarVisible40": 0,
    "StarVisible41": 0,
    "StarVisible42": 0,
    "StarVisible5": 69,
    "StarVisible6": 73,
    "StarVisible7": 77,
    "StarVisible8": 81,
    "StarVisible9": 85,
    "Subtitle1": 0,
    "Subtitle2": 105,
    "Supervisor_DataCard1": 52,
    "Supervisor_DataCard3": 114,
    "Supervisor_DataCard4": 0,
    "Task Order #_DataCard1": 50,
    "Task Order #_DataCard3": 112,
    "Task Order #_DataCard4": 0,
    "Task Order Name_DataCard1": 51,
    "Task Order Name_DataCard3": 113,
    "Task Order Name_DataCard4": 0,
    "Title1": 92,
    "Title2": 104,
    "Title3": 0,
    "Welcome": 16
  },
  "ResourcesJsonIndices": {
    "Image-chartim": 1,
    "Image-ia_comments": 3,
    "Image-iaform_first-1": 2,
    "Image-idasda-1": 4,
    "Image-Logo": 5,
    "Image-Logo_1": 6,
    "Image-logo_2": 7,
    "Image-NIS_Blue_logo": 8,
    "Image-NIS_New_2018_Logo": 9,
    "Image-SampleImage": 0,
    "Image-snippemtasd": 10,
    "Image-snippemtasd_1": 11
  },
  "RuleScreenIdWithoutScreen": {},
  "TemplateVersions": {},
  "VolatileProperties": {
    "AnalysisLoadTime": 0.4516051,
    "ControlCount": {
      "1bed1ce7b7404ccfafa05f0c3d1eabfe": 4,
      "1fe5cb6d6d5c424db75d7e843c1d26d9": 1,
      "5215c742aeea4048a853e8e745619b28": 2,
      "b9e9c7020717474292bbfd84c70fae58": 3,
      "button": 7,
      "e13589d35384415b90784ea27e3eb7e4": 1,
      "form": 3,
      "gallery": 2,
      "galleryTemplate": 2,
      "icon": 5,
      "image": 5,
      "label": 66,
      "rectangle": 5,
      "screen": 5,
      "text": 19,
      "typedDataCard": 18
    },
    "DeserializationLoadTime": 0.9992825
  },
  "WasLocalDatabaseReferencesEmpty": true
}